{
  "metadata": {
    "matchId": "match-1783707161123",
    "map": "alpine_mountains_3p",
    "players": 3,
    "status": "stopped",
    "duration": "0h 0m 0s",
    "ticks": 100,
    "createdAt": "2026-07-10T18:12:41.123Z",
    "recordedAt": "2026-07-10T18:12:41.124Z"
  },
  "statistics": {
    "totalEvents": 65,
    "eventCounts": {
      "match:started": 1,
      "observation:received": 21,
      "decision:completed": 21,
      "command:executed": 21,
      "match:ended": 1
    },
    "timelineEntries": 65,
    "totalDurationSeconds": 0.001
  },
  "config": {
    "matchId": "match-1783707161123",
    "map": "alpine_mountains_3p",
    "players": [
      {
        "id": 1,
        "name": "P1",
        "civilization": "Athens",
        "aiModel": "model-a",
        "aiPrompt": "prompt-a"
      },
      {
        "id": 2,
        "name": "P2",
        "civilization": "Rome",
        "aiModel": "model-b",
        "aiPrompt": "prompt-b"
      },
      {
        "id": 3,
        "name": "P3",
        "civilization": "Carthage",
        "aiModel": "model-c",
        "aiPrompt": "prompt-c"
      }
    ]
  },
  "timeline": {
    "entries": [
      {
        "timestamp": "2026-07-10T18:12:41.123Z",
        "elapsedSeconds": 0,
        "event": "match:started",
        "data": {
          "matchId": "match-1783707161123",
          "map": "alpine_mountains_3p",
          "players": 3
        }
      },
      {
        "timestamp": "2026-07-10T18:12:41.123Z",
        "elapsedSeconds": 0,
        "event": "observation:received",
        "data": {
          "tick": 0,
          "playerId": 1
        }
      },
      {
        "timestamp": "2026-07-10T18:12:41.123Z",
        "elapsedSeconds": 0,
        "event": "decision:completed",
        "data": {
          "tick": 0,
          "playerId": 1
        }
      },
      {
        "timestamp": "2026-07-10T18:12:41.123Z",
        "elapsedSeconds": 0,
        "event": "command:executed",
        "data": {
          "tick": 0,
          "playerId": 1
        }
      },
      {
        "timestamp": "2026-07-10T18:12:41.123Z",
        "elapsedSeconds": 0,
        "event": "observation:received",
        "data": {
          "tick": 5,
          "playerId": 1
        }
      },
      {
        "timestamp": "2026-07-10T18:12:41.123Z",
        "elapsedSeconds": 0,
        "event": "decision:completed",
        "data": {
          "tick": 5,
          "playerId": 1
        }
      },
      {
        "timestamp": "2026-07-10T18:12:41.123Z",
        "elapsedSeconds": 0,
        "event": "command:executed",
        "data": {
          "tick": 5,
          "playerId": 1
        }
      },
      {
        "timestamp": "2026-07-10T18:12:41.123Z",
        "elapsedSeconds": 0,
        "event": "observation:received",
        "data": {
          "tick": 10,
          "playerId": 1
        }
      },
      {
        "timestamp": "2026-07-10T18:12:41.123Z",
        "elapsedSeconds": 0,
        "event": "decision:completed",
        "data": {
          "tick": 10,
          "playerId": 1
        }
      },
      {
        "timestamp": "2026-07-10T18:12:41.123Z",
        "elapsedSeconds": 0,
        "event": "command:executed",
        "data": {
          "tick": 10,
          "playerId": 1
        }
      },
      {
        "timestamp": "2026-07-10T18:12:41.123Z",
        "elapsedSeconds": 0,
        "event": "observation:received",
        "data": {
          "tick": 15,
          "playerId": 1
        }
      },
      {
        "timestamp": "2026-07-10T18:12:41.123Z",
        "elapsedSeconds": 0,
        "event": "decision:completed",
        "data": {
          "tick": 15,
          "playerId": 1
        }
      },
      {
        "timestamp": "2026-07-10T18:12:41.123Z",
        "elapsedSeconds": 0,
        "event": "command:executed",
        "data": {
          "tick": 15,
          "playerId": 1
        }
      },
      {
        "timestamp": "2026-07-10T18:12:41.123Z",
        "elapsedSeconds": 0,
        "event": "observation:received",
        "data": {
          "tick": 20,
          "playerId": 1
        }
      },
      {
        "timestamp": "2026-07-10T18:12:41.123Z",
        "elapsedSeconds": 0,
        "event": "decision:completed",
        "data": {
          "tick": 20,
          "playerId": 1
        }
      },
      {
        "timestamp": "2026-07-10T18:12:41.123Z",
        "elapsedSeconds": 0,
        "event": "command:executed",
        "data": {
          "tick": 20,
          "playerId": 1
        }
      },
      {
        "timestamp": "2026-07-10T18:12:41.123Z",
        "elapsedSeconds": 0,
        "event": "observation:received",
        "data": {
          "tick": 25,
          "playerId": 1
        }
      },
      {
        "timestamp": "2026-07-10T18:12:41.123Z",
        "elapsedSeconds": 0,
        "event": "decision:completed",
        "data": {
          "tick": 25,
          "playerId": 1
        }
      },
      {
        "timestamp": "2026-07-10T18:12:41.123Z",
        "elapsedSeconds": 0,
        "event": "command:executed",
        "data": {
          "tick": 25,
          "playerId": 1
        }
      },
      {
        "timestamp": "2026-07-10T18:12:41.123Z",
        "elapsedSeconds": 0,
        "event": "observation:received",
        "data": {
          "tick": 30,
          "playerId": 1
        }
      },
      {
        "timestamp": "2026-07-10T18:12:41.123Z",
        "elapsedSeconds": 0,
        "event": "decision:completed",
        "data": {
          "tick": 30,
          "playerId": 1
        }
      },
      {
        "timestamp": "2026-07-10T18:12:41.123Z",
        "elapsedSeconds": 0,
        "event": "command:executed",
        "data": {
          "tick": 30,
          "playerId": 1
        }
      },
      {
        "timestamp": "2026-07-10T18:12:41.123Z",
        "elapsedSeconds": 0,
        "event": "observation:received",
        "data": {
          "tick": 35,
          "playerId": 1
        }
      },
      {
        "timestamp": "2026-07-10T18:12:41.123Z",
        "elapsedSeconds": 0,
        "event": "decision:completed",
        "data": {
          "tick": 35,
          "playerId": 1
        }
      },
      {
        "timestamp": "2026-07-10T18:12:41.123Z",
        "elapsedSeconds": 0,
        "event": "command:executed",
        "data": {
          "tick": 35,
          "playerId": 1
        }
      },
      {
        "timestamp": "2026-07-10T18:12:41.123Z",
        "elapsedSeconds": 0,
        "event": "observation:received",
        "data": {
          "tick": 40,
          "playerId": 1
        }
      },
      {
        "timestamp": "2026-07-10T18:12:41.123Z",
        "elapsedSeconds": 0,
        "event": "decision:completed",
        "data": {
          "tick": 40,
          "playerId": 1
        }
      },
      {
        "timestamp": "2026-07-10T18:12:41.123Z",
        "elapsedSeconds": 0,
        "event": "command:executed",
        "data": {
          "tick": 40,
          "playerId": 1
        }
      },
      {
        "timestamp": "2026-07-10T18:12:41.124Z",
        "elapsedSeconds": 0.001,
        "event": "observation:received",
        "data": {
          "tick": 45,
          "playerId": 1
        }
      },
      {
        "timestamp": "2026-07-10T18:12:41.124Z",
        "elapsedSeconds": 0.001,
        "event": "decision:completed",
        "data": {
          "tick": 45,
          "playerId": 1
        }
      },
      {
        "timestamp": "2026-07-10T18:12:41.124Z",
        "elapsedSeconds": 0.001,
        "event": "command:executed",
        "data": {
          "tick": 45,
          "playerId": 1
        }
      },
      {
        "timestamp": "2026-07-10T18:12:41.124Z",
        "elapsedSeconds": 0.001,
        "event": "observation:received",
        "data": {
          "tick": 50,
          "playerId": 1
        }
      },
      {
        "timestamp": "2026-07-10T18:12:41.124Z",
        "elapsedSeconds": 0.001,
        "event": "decision:completed",
        "data": {
          "tick": 50,
          "playerId": 1
        }
      },
      {
        "timestamp": "2026-07-10T18:12:41.124Z",
        "elapsedSeconds": 0.001,
        "event": "command:executed",
        "data": {
          "tick": 50,
          "playerId": 1
        }
      },
      {
        "timestamp": "2026-07-10T18:12:41.124Z",
        "elapsedSeconds": 0.001,
        "event": "observation:received",
        "data": {
          "tick": 55,
          "playerId": 1
        }
      },
      {
        "timestamp": "2026-07-10T18:12:41.124Z",
        "elapsedSeconds": 0.001,
        "event": "decision:completed",
        "data": {
          "tick": 55,
          "playerId": 1
        }
      },
      {
        "timestamp": "2026-07-10T18:12:41.124Z",
        "elapsedSeconds": 0.001,
        "event": "command:executed",
        "data": {
          "tick": 55,
          "playerId": 1
        }
      },
      {
        "timestamp": "2026-07-10T18:12:41.124Z",
        "elapsedSeconds": 0.001,
        "event": "observation:received",
        "data": {
          "tick": 60,
          "playerId": 1
        }
      },
      {
        "timestamp": "2026-07-10T18:12:41.124Z",
        "elapsedSeconds": 0.001,
        "event": "decision:completed",
        "data": {
          "tick": 60,
          "playerId": 1
        }
      },
      {
        "timestamp": "2026-07-10T18:12:41.124Z",
        "elapsedSeconds": 0.001,
        "event": "command:executed",
        "data": {
          "tick": 60,
          "playerId": 1
        }
      },
      {
        "timestamp": "2026-07-10T18:12:41.124Z",
        "elapsedSeconds": 0.001,
        "event": "observation:received",
        "data": {
          "tick": 65,
          "playerId": 1
        }
      },
      {
        "timestamp": "2026-07-10T18:12:41.124Z",
        "elapsedSeconds": 0.001,
        "event": "decision:completed",
        "data": {
          "tick": 65,
          "playerId": 1
        }
      },
      {
        "timestamp": "2026-07-10T18:12:41.124Z",
        "elapsedSeconds": 0.001,
        "event": "command:executed",
        "data": {
          "tick": 65,
          "playerId": 1
        }
      },
      {
        "timestamp": "2026-07-10T18:12:41.124Z",
        "elapsedSeconds": 0.001,
        "event": "observation:received",
        "data": {
          "tick": 70,
          "playerId": 1
        }
      },
      {
        "timestamp": "2026-07-10T18:12:41.124Z",
        "elapsedSeconds": 0.001,
        "event": "decision:completed",
        "data": {
          "tick": 70,
          "playerId": 1
        }
      },
      {
        "timestamp": "2026-07-10T18:12:41.124Z",
        "elapsedSeconds": 0.001,
        "event": "command:executed",
        "data": {
          "tick": 70,
          "playerId": 1
        }
      },
      {
        "timestamp": "2026-07-10T18:12:41.124Z",
        "elapsedSeconds": 0.001,
        "event": "observation:received",
        "data": {
          "tick": 75,
          "playerId": 1
        }
      },
      {
        "timestamp": "2026-07-10T18:12:41.124Z",
        "elapsedSeconds": 0.001,
        "event": "decision:completed",
        "data": {
          "tick": 75,
          "playerId": 1
        }
      },
      {
        "timestamp": "2026-07-10T18:12:41.124Z",
        "elapsedSeconds": 0.001,
        "event": "command:executed",
        "data": {
          "tick": 75,
          "playerId": 1
        }
      },
      {
        "timestamp": "2026-07-10T18:12:41.124Z",
        "elapsedSeconds": 0.001,
        "event": "observation:received",
        "data": {
          "tick": 80,
          "playerId": 1
        }
      },
      {
        "timestamp": "2026-07-10T18:12:41.124Z",
        "elapsedSeconds": 0.001,
        "event": "decision:completed",
        "data": {
          "tick": 80,
          "playerId": 1
        }
      },
      {
        "timestamp": "2026-07-10T18:12:41.124Z",
        "elapsedSeconds": 0.001,
        "event": "command:executed",
        "data": {
          "tick": 80,
          "playerId": 1
        }
      },
      {
        "timestamp": "2026-07-10T18:12:41.124Z",
        "elapsedSeconds": 0.001,
        "event": "observation:received",
        "data": {
          "tick": 85,
          "playerId": 1
        }
      },
      {
        "timestamp": "2026-07-10T18:12:41.124Z",
        "elapsedSeconds": 0.001,
        "event": "decision:completed",
        "data": {
          "tick": 85,
          "playerId": 1
        }
      },
      {
        "timestamp": "2026-07-10T18:12:41.124Z",
        "elapsedSeconds": 0.001,
        "event": "command:executed",
        "data": {
          "tick": 85,
          "playerId": 1
        }
      },
      {
        "timestamp": "2026-07-10T18:12:41.124Z",
        "elapsedSeconds": 0.001,
        "event": "observation:received",
        "data": {
          "tick": 90,
          "playerId": 1
        }
      },
      {
        "timestamp": "2026-07-10T18:12:41.124Z",
        "elapsedSeconds": 0.001,
        "event": "decision:completed",
        "data": {
          "tick": 90,
          "playerId": 1
        }
      },
      {
        "timestamp": "2026-07-10T18:12:41.124Z",
        "elapsedSeconds": 0.001,
        "event": "command:executed",
        "data": {
          "tick": 90,
          "playerId": 1
        }
      },
      {
        "timestamp": "2026-07-10T18:12:41.124Z",
        "elapsedSeconds": 0.001,
        "event": "observation:received",
        "data": {
          "tick": 95,
          "playerId": 1
        }
      },
      {
        "timestamp": "2026-07-10T18:12:41.124Z",
        "elapsedSeconds": 0.001,
        "event": "decision:completed",
        "data": {
          "tick": 95,
          "playerId": 1
        }
      },
      {
        "timestamp": "2026-07-10T18:12:41.124Z",
        "elapsedSeconds": 0.001,
        "event": "command:executed",
        "data": {
          "tick": 95,
          "playerId": 1
        }
      },
      {
        "timestamp": "2026-07-10T18:12:41.124Z",
        "elapsedSeconds": 0.001,
        "event": "observation:received",
        "data": {
          "tick": 100,
          "playerId": 1
        }
      },
      {
        "timestamp": "2026-07-10T18:12:41.124Z",
        "elapsedSeconds": 0.001,
        "event": "decision:completed",
        "data": {
          "tick": 100,
          "playerId": 1
        }
      },
      {
        "timestamp": "2026-07-10T18:12:41.124Z",
        "elapsedSeconds": 0.001,
        "event": "command:executed",
        "data": {
          "tick": 100,
          "playerId": 1
        }
      },
      {
        "timestamp": "2026-07-10T18:12:41.124Z",
        "elapsedSeconds": 0.001,
        "event": "match:ended",
        "data": {
          "matchId": "match-1783707161123",
          "winner": 1,
          "ticks": 100
        }
      }
    ],
    "startTime": "2026-07-10T18:12:41.123Z"
  },
  "events": {
    "entries": [
      {
        "event": "match:started",
        "data": {
          "matchId": "match-1783707161123",
          "map": "alpine_mountains_3p",
          "players": [
            {
              "id": 1,
              "name": "P1",
              "civilization": "Athens"
            },
            {
              "id": 2,
              "name": "P2",
              "civilization": "Rome"
            },
            {
              "id": 3,
              "name": "P3",
              "civilization": "Carthage"
            }
          ],
          "timestamp": "2026-07-10T18:12:41.123Z"
        },
        "timestamp": "2026-07-10T18:12:41.123Z"
      },
      {
        "event": "observation:received",
        "data": {
          "matchId": "match-1783707161123",
          "playerId": 1,
          "playerName": "P1",
          "tick": 0,
          "observation": {
            "gameTime": 0,
            "resources": {
              "wood": 546.5755251906187,
              "stone": 563.1889356258653,
              "food": 561.1687713322862
            },
            "units": 37,
            "buildings": 9
          },
          "timestamp": "2026-07-10T18:12:41.123Z"
        },
        "timestamp": "2026-07-10T18:12:41.123Z"
      },
      {
        "event": "decision:completed",
        "data": {
          "matchId": "match-1783707161123",
          "playerId": 1,
          "playerName": "P1",
          "tick": 0,
          "model": "model-a",
          "prompt": "prompt-a",
          "decision": {
            "objective": "Build initial economy",
            "confidence": 0.7902370807608647,
            "reasoning": "Strategic decision based on game state"
          },
          "latency": 1136.9915445595047,
          "cost": 0.0001,
          "timestamp": "2026-07-10T18:12:41.123Z"
        },
        "timestamp": "2026-07-10T18:12:41.123Z"
      },
      {
        "event": "command:executed",
        "data": {
          "matchId": "match-1783707161123",
          "playerId": 1,
          "playerName": "P1",
          "tick": 0,
          "command": {
            "action": "build",
            "target": "unit-94"
          },
          "isValid": true,
          "timestamp": "2026-07-10T18:12:41.123Z"
        },
        "timestamp": "2026-07-10T18:12:41.123Z"
      },
      {
        "event": "observation:received",
        "data": {
          "matchId": "match-1783707161123",
          "playerId": 1,
          "playerName": "P1",
          "tick": 5,
          "observation": {
            "gameTime": 0.5,
            "resources": {
              "wood": 733.0039335266856,
              "stone": 584.9712776257629,
              "food": 484.10308209932055
            },
            "units": 27,
            "buildings": 14
          },
          "timestamp": "2026-07-10T18:12:41.123Z"
        },
        "timestamp": "2026-07-10T18:12:41.123Z"
      },
      {
        "event": "decision:completed",
        "data": {
          "matchId": "match-1783707161123",
          "playerId": 1,
          "playerName": "P1",
          "tick": 5,
          "model": "model-a",
          "prompt": "prompt-a",
          "decision": {
            "objective": "Build initial economy",
            "confidence": 0.7838461228975161,
            "reasoning": "Strategic decision based on game state"
          },
          "latency": 858.7933832145778,
          "cost": 0.0001,
          "timestamp": "2026-07-10T18:12:41.123Z"
        },
        "timestamp": "2026-07-10T18:12:41.123Z"
      },
      {
        "event": "command:executed",
        "data": {
          "matchId": "match-1783707161123",
          "playerId": 1,
          "playerName": "P1",
          "tick": 5,
          "command": {
            "action": "train",
            "target": "unit-88"
          },
          "isValid": true,
          "timestamp": "2026-07-10T18:12:41.123Z"
        },
        "timestamp": "2026-07-10T18:12:41.123Z"
      },
      {
        "event": "observation:received",
        "data": {
          "matchId": "match-1783707161123",
          "playerId": 1,
          "playerName": "P1",
          "tick": 10,
          "observation": {
            "gameTime": 1,
            "resources": {
              "wood": 523.423898917299,
              "stone": 427.26271845635597,
              "food": 474.99301960752587
            },
            "units": 49,
            "buildings": 13
          },
          "timestamp": "2026-07-10T18:12:41.123Z"
        },
        "timestamp": "2026-07-10T18:12:41.123Z"
      },
      {
        "event": "decision:completed",
        "data": {
          "matchId": "match-1783707161123",
          "playerId": 1,
          "playerName": "P1",
          "tick": 10,
          "model": "model-a",
          "prompt": "prompt-a",
          "decision": {
            "objective": "Build initial economy",
            "confidence": 0.9986239502737213,
            "reasoning": "Strategic decision based on game state"
          },
          "latency": 927.2767278112199,
          "cost": 0.0001,
          "timestamp": "2026-07-10T18:12:41.123Z"
        },
        "timestamp": "2026-07-10T18:12:41.123Z"
      },
      {
        "event": "command:executed",
        "data": {
          "matchId": "match-1783707161123",
          "playerId": 1,
          "playerName": "P1",
          "tick": 10,
          "command": {
            "action": "train",
            "target": "unit-7"
          },
          "isValid": true,
          "timestamp": "2026-07-10T18:12:41.123Z"
        },
        "timestamp": "2026-07-10T18:12:41.123Z"
      },
      {
        "event": "observation:received",
        "data": {
          "matchId": "match-1783707161123",
          "playerId": 1,
          "playerName": "P1",
          "tick": 15,
          "observation": {
            "gameTime": 1.5,
            "resources": {
              "wood": 593.2145963776203,
              "stone": 422.1037862426161,
              "food": 447.7397794439943
            },
            "units": 23,
            "buildings": 14
          },
          "timestamp": "2026-07-10T18:12:41.123Z"
        },
        "timestamp": "2026-07-10T18:12:41.123Z"
      },
      {
        "event": "decision:completed",
        "data": {
          "matchId": "match-1783707161123",
          "playerId": 1,
          "playerName": "P1",
          "tick": 15,
          "model": "model-a",
          "prompt": "prompt-a",
          "decision": {
            "objective": "Build initial economy",
            "confidence": 0.7880355264899522,
            "reasoning": "Strategic decision based on game state"
          },
          "latency": 1166.2758965209557,
          "cost": 0.0001,
          "timestamp": "2026-07-10T18:12:41.123Z"
        },
        "timestamp": "2026-07-10T18:12:41.123Z"
      },
      {
        "event": "command:executed",
        "data": {
          "matchId": "match-1783707161123",
          "playerId": 1,
          "playerName": "P1",
          "tick": 15,
          "command": {
            "action": "train",
            "target": "unit-88"
          },
          "isValid": true,
          "timestamp": "2026-07-10T18:12:41.123Z"
        },
        "timestamp": "2026-07-10T18:12:41.123Z"
      },
      {
        "event": "observation:received",
        "data": {
          "matchId": "match-1783707161123",
          "playerId": 1,
          "playerName": "P1",
          "tick": 20,
          "observation": {
            "gameTime": 2,
            "resources": {
              "wood": 580.2307195257105,
              "stone": 374.4726050481065,
              "food": 419.94729182355076
            },
            "units": 48,
            "buildings": 6
          },
          "timestamp": "2026-07-10T18:12:41.123Z"
        },
        "timestamp": "2026-07-10T18:12:41.123Z"
      },
      {
        "event": "decision:completed",
        "data": {
          "matchId": "match-1783707161123",
          "playerId": 1,
          "playerName": "P1",
          "tick": 20,
          "model": "model-a",
          "prompt": "prompt-a",
          "decision": {
            "objective": "Build initial economy",
            "confidence": 0.757326844533123,
            "reasoning": "Strategic decision based on game state"
          },
          "latency": 1126.6799449853545,
          "cost": 0.0001,
          "timestamp": "2026-07-10T18:12:41.123Z"
        },
        "timestamp": "2026-07-10T18:12:41.123Z"
      },
      {
        "event": "command:executed",
        "data": {
          "matchId": "match-1783707161123",
          "playerId": 1,
          "playerName": "P1",
          "tick": 20,
          "command": {
            "action": "train",
            "target": "unit-15"
          },
          "isValid": true,
          "timestamp": "2026-07-10T18:12:41.123Z"
        },
        "timestamp": "2026-07-10T18:12:41.123Z"
      },
      {
        "event": "observation:received",
        "data": {
          "matchId": "match-1783707161123",
          "playerId": 1,
          "playerName": "P1",
          "tick": 25,
          "observation": {
            "gameTime": 2.5,
            "resources": {
              "wood": 999.5126743493247,
              "stone": 406.61049536655594,
              "food": 541.2515895398595
            },
            "units": 32,
            "buildings": 12
          },
          "timestamp": "2026-07-10T18:12:41.123Z"
        },
        "timestamp": "2026-07-10T18:12:41.123Z"
      },
      {
        "event": "decision:completed",
        "data": {
          "matchId": "match-1783707161123",
          "playerId": 1,
          "playerName": "P1",
          "tick": 25,
          "model": "model-a",
          "prompt": "prompt-a",
          "decision": {
            "objective": "Establish military presence",
            "confidence": 0.9655819755978752,
            "reasoning": "Strategic decision based on game state"
          },
          "latency": 1155.2391893375711,
          "cost": 0.0001,
          "timestamp": "2026-07-10T18:12:41.123Z"
        },
        "timestamp": "2026-07-10T18:12:41.123Z"
      },
      {
        "event": "command:executed",
        "data": {
          "matchId": "match-1783707161123",
          "playerId": 1,
          "playerName": "P1",
          "tick": 25,
          "command": {
            "action": "train",
            "target": "unit-27"
          },
          "isValid": true,
          "timestamp": "2026-07-10T18:12:41.123Z"
        },
        "timestamp": "2026-07-10T18:12:41.123Z"
      },
      {
        "event": "observation:received",
        "data": {
          "matchId": "match-1783707161123",
          "playerId": 1,
          "playerName": "P1",
          "tick": 30,
          "observation": {
            "gameTime": 3,
            "resources": {
              "wood": 655.772442743756,
              "stone": 457.6773247067245,
              "food": 443.43492973889863
            },
            "units": 38,
            "buildings": 5
          },
          "timestamp": "2026-07-10T18:12:41.123Z"
        },
        "timestamp": "2026-07-10T18:12:41.123Z"
      },
      {
        "event": "decision:completed",
        "data": {
          "matchId": "match-1783707161123",
          "playerId": 1,
          "playerName": "P1",
          "tick": 30,
          "model": "model-a",
          "prompt": "prompt-a",
          "decision": {
            "objective": "Establish military presence",
            "confidence": 0.9661467122383227,
            "reasoning": "Strategic decision based on game state"
          },
          "latency": 1119.2120622142943,
          "cost": 0.0001,
          "timestamp": "2026-07-10T18:12:41.123Z"
        },
        "timestamp": "2026-07-10T18:12:41.123Z"
      },
      {
        "event": "command:executed",
        "data": {
          "matchId": "match-1783707161123",
          "playerId": 1,
          "playerName": "P1",
          "tick": 30,
          "command": {
            "action": "train",
            "target": "unit-14"
          },
          "isValid": true,
          "timestamp": "2026-07-10T18:12:41.123Z"
        },
        "timestamp": "2026-07-10T18:12:41.123Z"
      },
      {
        "event": "observation:received",
        "data": {
          "matchId": "match-1783707161123",
          "playerId": 1,
          "playerName": "P1",
          "tick": 35,
          "observation": {
            "gameTime": 3.5,
            "resources": {
              "wood": 780.8853625964443,
              "stone": 372.2752902141383,
              "food": 542.5554756090589
            },
            "units": 39,
            "buildings": 9
          },
          "timestamp": "2026-07-10T18:12:41.123Z"
        },
        "timestamp": "2026-07-10T18:12:41.123Z"
      },
      {
        "event": "decision:completed",
        "data": {
          "matchId": "match-1783707161123",
          "playerId": 1,
          "playerName": "P1",
          "tick": 35,
          "model": "model-a",
          "prompt": "prompt-a",
          "decision": {
            "objective": "Establish military presence",
            "confidence": 0.7283787642289508,
            "reasoning": "Strategic decision based on game state"
          },
          "latency": 1137.8385423508448,
          "cost": 0.0001,
          "timestamp": "2026-07-10T18:12:41.123Z"
        },
        "timestamp": "2026-07-10T18:12:41.123Z"
      },
      {
        "event": "command:executed",
        "data": {
          "matchId": "match-1783707161123",
          "playerId": 1,
          "playerName": "P1",
          "tick": 35,
          "command": {
            "action": "train",
            "target": "unit-54"
          },
          "isValid": true,
          "timestamp": "2026-07-10T18:12:41.123Z"
        },
        "timestamp": "2026-07-10T18:12:41.123Z"
      },
      {
        "event": "observation:received",
        "data": {
          "matchId": "match-1783707161123",
          "playerId": 1,
          "playerName": "P1",
          "tick": 40,
          "observation": {
            "gameTime": 4,
            "resources": {
              "wood": 875.5934580390972,
              "stone": 562.3467415407983,
              "food": 544.4734729354689
            },
            "units": 28,
            "buildings": 6
          },
          "timestamp": "2026-07-10T18:12:41.123Z"
        },
        "timestamp": "2026-07-10T18:12:41.123Z"
      },
      {
        "event": "decision:completed",
        "data": {
          "matchId": "match-1783707161123",
          "playerId": 1,
          "playerName": "P1",
          "tick": 40,
          "model": "model-a",
          "prompt": "prompt-a",
          "decision": {
            "objective": "Establish military presence",
            "confidence": 0.7568851954902246,
            "reasoning": "Strategic decision based on game state"
          },
          "latency": 1016.9601241235735,
          "cost": 0.0001,
          "timestamp": "2026-07-10T18:12:41.123Z"
        },
        "timestamp": "2026-07-10T18:12:41.123Z"
      },
      {
        "event": "command:executed",
        "data": {
          "matchId": "match-1783707161123",
          "playerId": 1,
          "playerName": "P1",
          "tick": 40,
          "command": {
            "action": "train",
            "target": "unit-46"
          },
          "isValid": true,
          "timestamp": "2026-07-10T18:12:41.123Z"
        },
        "timestamp": "2026-07-10T18:12:41.123Z"
      },
      {
        "event": "observation:received",
        "data": {
          "matchId": "match-1783707161123",
          "playerId": 1,
          "playerName": "P1",
          "tick": 45,
          "observation": {
            "gameTime": 4.5,
            "resources": {
              "wood": 761.1284537892901,
              "stone": 492.69548686583704,
              "food": 532.9977165794752
            },
            "units": 46,
            "buildings": 9
          },
          "timestamp": "2026-07-10T18:12:41.123Z"
        },
        "timestamp": "2026-07-10T18:12:41.123Z"
      },
      {
        "event": "decision:completed",
        "data": {
          "matchId": "match-1783707161123",
          "playerId": 1,
          "playerName": "P1",
          "tick": 45,
          "model": "model-a",
          "prompt": "prompt-a",
          "decision": {
            "objective": "Establish military presence",
            "confidence": 0.8115806755340091,
            "reasoning": "Strategic decision based on game state"
          },
          "latency": 1162.3389162295032,
          "cost": 0.0001,
          "timestamp": "2026-07-10T18:12:41.124Z"
        },
        "timestamp": "2026-07-10T18:12:41.124Z"
      },
      {
        "event": "command:executed",
        "data": {
          "matchId": "match-1783707161123",
          "playerId": 1,
          "playerName": "P1",
          "tick": 45,
          "command": {
            "action": "train",
            "target": "unit-20"
          },
          "isValid": true,
          "timestamp": "2026-07-10T18:12:41.124Z"
        },
        "timestamp": "2026-07-10T18:12:41.124Z"
      },
      {
        "event": "observation:received",
        "data": {
          "matchId": "match-1783707161123",
          "playerId": 1,
          "playerName": "P1",
          "tick": 50,
          "observation": {
            "gameTime": 5,
            "resources": {
              "wood": 917.6911727286702,
              "stone": 452.1355167760162,
              "food": 446.3748558734241
            },
            "units": 38,
            "buildings": 11
          },
          "timestamp": "2026-07-10T18:12:41.124Z"
        },
        "timestamp": "2026-07-10T18:12:41.124Z"
      },
      {
        "event": "decision:completed",
        "data": {
          "matchId": "match-1783707161123",
          "playerId": 1,
          "playerName": "P1",
          "tick": 50,
          "model": "model-a",
          "prompt": "prompt-a",
          "decision": {
            "objective": "Expand territory",
            "confidence": 0.7024300472753323,
            "reasoning": "Strategic decision based on game state"
          },
          "latency": 972.9732405055196,
          "cost": 0.0001,
          "timestamp": "2026-07-10T18:12:41.124Z"
        },
        "timestamp": "2026-07-10T18:12:41.124Z"
      },
      {
        "event": "command:executed",
        "data": {
          "matchId": "match-1783707161123",
          "playerId": 1,
          "playerName": "P1",
          "tick": 50,
          "command": {
            "action": "train",
            "target": "unit-97"
          },
          "isValid": true,
          "timestamp": "2026-07-10T18:12:41.124Z"
        },
        "timestamp": "2026-07-10T18:12:41.124Z"
      },
      {
        "event": "observation:received",
        "data": {
          "matchId": "match-1783707161123",
          "playerId": 1,
          "playerName": "P1",
          "tick": 55,
          "observation": {
            "gameTime": 5.5,
            "resources": {
              "wood": 542.5337859412689,
              "stone": 409.804833762885,
              "food": 423.0689844068776
            },
            "units": 24,
            "buildings": 5
          },
          "timestamp": "2026-07-10T18:12:41.124Z"
        },
        "timestamp": "2026-07-10T18:12:41.124Z"
      },
      {
        "event": "decision:completed",
        "data": {
          "matchId": "match-1783707161123",
          "playerId": 1,
          "playerName": "P1",
          "tick": 55,
          "model": "model-a",
          "prompt": "prompt-a",
          "decision": {
            "objective": "Expand territory",
            "confidence": 0.8337951078923884,
            "reasoning": "Strategic decision based on game state"
          },
          "latency": 1006.08238998734,
          "cost": 0.0001,
          "timestamp": "2026-07-10T18:12:41.124Z"
        },
        "timestamp": "2026-07-10T18:12:41.124Z"
      },
      {
        "event": "command:executed",
        "data": {
          "matchId": "match-1783707161123",
          "playerId": 1,
          "playerName": "P1",
          "tick": 55,
          "command": {
            "action": "train",
            "target": "unit-75"
          },
          "isValid": true,
          "timestamp": "2026-07-10T18:12:41.124Z"
        },
        "timestamp": "2026-07-10T18:12:41.124Z"
      },
      {
        "event": "observation:received",
        "data": {
          "matchId": "match-1783707161123",
          "playerId": 1,
          "playerName": "P1",
          "tick": 60,
          "observation": {
            "gameTime": 6,
            "resources": {
              "wood": 705.7222300491001,
              "stone": 596.293020235779,
              "food": 532.7940281931301
            },
            "units": 44,
            "buildings": 5
          },
          "timestamp": "2026-07-10T18:12:41.124Z"
        },
        "timestamp": "2026-07-10T18:12:41.124Z"
      },
      {
        "event": "decision:completed",
        "data": {
          "matchId": "match-1783707161123",
          "playerId": 1,
          "playerName": "P1",
          "tick": 60,
          "model": "model-a",
          "prompt": "prompt-a",
          "decision": {
            "objective": "Expand territory",
            "confidence": 0.8544715028048073,
            "reasoning": "Strategic decision based on game state"
          },
          "latency": 812.0651043988303,
          "cost": 0.0001,
          "timestamp": "2026-07-10T18:12:41.124Z"
        },
        "timestamp": "2026-07-10T18:12:41.124Z"
      },
      {
        "event": "command:executed",
        "data": {
          "matchId": "match-1783707161123",
          "playerId": 1,
          "playerName": "P1",
          "tick": 60,
          "command": {
            "action": "train",
            "target": "unit-11"
          },
          "isValid": true,
          "timestamp": "2026-07-10T18:12:41.124Z"
        },
        "timestamp": "2026-07-10T18:12:41.124Z"
      },
      {
        "event": "observation:received",
        "data": {
          "matchId": "match-1783707161123",
          "playerId": 1,
          "playerName": "P1",
          "tick": 65,
          "observation": {
            "gameTime": 6.5,
            "resources": {
              "wood": 578.0915761616869,
              "stone": 566.5543144758742,
              "food": 465.28562522675344
            },
            "units": 38,
            "buildings": 8
          },
          "timestamp": "2026-07-10T18:12:41.124Z"
        },
        "timestamp": "2026-07-10T18:12:41.124Z"
      },
      {
        "event": "decision:completed",
        "data": {
          "matchId": "match-1783707161123",
          "playerId": 1,
          "playerName": "P1",
          "tick": 65,
          "model": "model-a",
          "prompt": "prompt-a",
          "decision": {
            "objective": "Expand territory",
            "confidence": 0.7824094951532048,
            "reasoning": "Strategic decision based on game state"
          },
          "latency": 1075.0786153985784,
          "cost": 0.0001,
          "timestamp": "2026-07-10T18:12:41.124Z"
        },
        "timestamp": "2026-07-10T18:12:41.124Z"
      },
      {
        "event": "command:executed",
        "data": {
          "matchId": "match-1783707161123",
          "playerId": 1,
          "playerName": "P1",
          "tick": 65,
          "command": {
            "action": "train",
            "target": "unit-22"
          },
          "isValid": true,
          "timestamp": "2026-07-10T18:12:41.124Z"
        },
        "timestamp": "2026-07-10T18:12:41.124Z"
      },
      {
        "event": "observation:received",
        "data": {
          "matchId": "match-1783707161123",
          "playerId": 1,
          "playerName": "P1",
          "tick": 70,
          "observation": {
            "gameTime": 7,
            "resources": {
              "wood": 752.0381238510864,
              "stone": 563.8125069006649,
              "food": 417.4602380302339
            },
            "units": 28,
            "buildings": 14
          },
          "timestamp": "2026-07-10T18:12:41.124Z"
        },
        "timestamp": "2026-07-10T18:12:41.124Z"
      },
      {
        "event": "decision:completed",
        "data": {
          "matchId": "match-1783707161123",
          "playerId": 1,
          "playerName": "P1",
          "tick": 70,
          "model": "model-a",
          "prompt": "prompt-a",
          "decision": {
            "objective": "Expand territory",
            "confidence": 0.9231950175569958,
            "reasoning": "Strategic decision based on game state"
          },
          "latency": 973.2829653688784,
          "cost": 0.0001,
          "timestamp": "2026-07-10T18:12:41.124Z"
        },
        "timestamp": "2026-07-10T18:12:41.124Z"
      },
      {
        "event": "command:executed",
        "data": {
          "matchId": "match-1783707161123",
          "playerId": 1,
          "playerName": "P1",
          "tick": 70,
          "command": {
            "action": "train",
            "target": "unit-77"
          },
          "isValid": true,
          "timestamp": "2026-07-10T18:12:41.124Z"
        },
        "timestamp": "2026-07-10T18:12:41.124Z"
      },
      {
        "event": "observation:received",
        "data": {
          "matchId": "match-1783707161123",
          "playerId": 1,
          "playerName": "P1",
          "tick": 75,
          "observation": {
            "gameTime": 7.5,
            "resources": {
              "wood": 835.6770875142909,
              "stone": 485.26997344338315,
              "food": 568.9959985748046
            },
            "units": 28,
            "buildings": 5
          },
          "timestamp": "2026-07-10T18:12:41.124Z"
        },
        "timestamp": "2026-07-10T18:12:41.124Z"
      },
      {
        "event": "decision:completed",
        "data": {
          "matchId": "match-1783707161123",
          "playerId": 1,
          "playerName": "P1",
          "tick": 75,
          "model": "model-a",
          "prompt": "prompt-a",
          "decision": {
            "objective": "Prepare for endgame",
            "confidence": 0.960050019974765,
            "reasoning": "Strategic decision based on game state"
          },
          "latency": 871.0399146744624,
          "cost": 0.0001,
          "timestamp": "2026-07-10T18:12:41.124Z"
        },
        "timestamp": "2026-07-10T18:12:41.124Z"
      },
      {
        "event": "command:executed",
        "data": {
          "matchId": "match-1783707161123",
          "playerId": 1,
          "playerName": "P1",
          "tick": 75,
          "command": {
            "action": "train",
            "target": "unit-20"
          },
          "isValid": true,
          "timestamp": "2026-07-10T18:12:41.124Z"
        },
        "timestamp": "2026-07-10T18:12:41.124Z"
      },
      {
        "event": "observation:received",
        "data": {
          "matchId": "match-1783707161123",
          "playerId": 1,
          "playerName": "P1",
          "tick": 80,
          "observation": {
            "gameTime": 8,
            "resources": {
              "wood": 670.8589974231184,
              "stone": 364.4958375494398,
              "food": 413.15344429083166
            },
            "units": 24,
            "buildings": 14
          },
          "timestamp": "2026-07-10T18:12:41.124Z"
        },
        "timestamp": "2026-07-10T18:12:41.124Z"
      },
      {
        "event": "decision:completed",
        "data": {
          "matchId": "match-1783707161123",
          "playerId": 1,
          "playerName": "P1",
          "tick": 80,
          "model": "model-a",
          "prompt": "prompt-a",
          "decision": {
            "objective": "Prepare for endgame",
            "confidence": 0.7095903214096906,
            "reasoning": "Strategic decision based on game state"
          },
          "latency": 939.9494974379884,
          "cost": 0.0001,
          "timestamp": "2026-07-10T18:12:41.124Z"
        },
        "timestamp": "2026-07-10T18:12:41.124Z"
      },
      {
        "event": "command:executed",
        "data": {
          "matchId": "match-1783707161123",
          "playerId": 1,
          "playerName": "P1",
          "tick": 80,
          "command": {
            "action": "train",
            "target": "unit-54"
          },
          "isValid": true,
          "timestamp": "2026-07-10T18:12:41.124Z"
        },
        "timestamp": "2026-07-10T18:12:41.124Z"
      },
      {
        "event": "observation:received",
        "data": {
          "matchId": "match-1783707161123",
          "playerId": 1,
          "playerName": "P1",
          "tick": 85,
          "observation": {
            "gameTime": 8.5,
            "resources": {
              "wood": 691.8031984923048,
              "stone": 350.1031552819368,
              "food": 487.53107124912117
            },
            "units": 36,
            "buildings": 10
          },
          "timestamp": "2026-07-10T18:12:41.124Z"
        },
        "timestamp": "2026-07-10T18:12:41.124Z"
      },
      {
        "event": "decision:completed",
        "data": {
          "matchId": "match-1783707161123",
          "playerId": 1,
          "playerName": "P1",
          "tick": 85,
          "model": "model-a",
          "prompt": "prompt-a",
          "decision": {
            "objective": "Prepare for endgame",
            "confidence": 0.8779733126198866,
            "reasoning": "Strategic decision based on game state"
          },
          "latency": 840.7130259415571,
          "cost": 0.0001,
          "timestamp": "2026-07-10T18:12:41.124Z"
        },
        "timestamp": "2026-07-10T18:12:41.124Z"
      },
      {
        "event": "command:executed",
        "data": {
          "matchId": "match-1783707161123",
          "playerId": 1,
          "playerName": "P1",
          "tick": 85,
          "command": {
            "action": "train",
            "target": "unit-85"
          },
          "isValid": true,
          "timestamp": "2026-07-10T18:12:41.124Z"
        },
        "timestamp": "2026-07-10T18:12:41.124Z"
      },
      {
        "event": "observation:received",
        "data": {
          "matchId": "match-1783707161123",
          "playerId": 1,
          "playerName": "P1",
          "tick": 90,
          "observation": {
            "gameTime": 9,
            "resources": {
              "wood": 781.4899277195018,
              "stone": 462.24220122008956,
              "food": 452.75364759562325
            },
            "units": 20,
            "buildings": 7
          },
          "timestamp": "2026-07-10T18:12:41.124Z"
        },
        "timestamp": "2026-07-10T18:12:41.124Z"
      },
      {
        "event": "decision:completed",
        "data": {
          "matchId": "match-1783707161123",
          "playerId": 1,
          "playerName": "P1",
          "tick": 90,
          "model": "model-a",
          "prompt": "prompt-a",
          "decision": {
            "objective": "Prepare for endgame",
            "confidence": 0.9401533005048119,
            "reasoning": "Strategic decision based on game state"
          },
          "latency": 920.6540449758536,
          "cost": 0.0001,
          "timestamp": "2026-07-10T18:12:41.124Z"
        },
        "timestamp": "2026-07-10T18:12:41.124Z"
      },
      {
        "event": "command:executed",
        "data": {
          "matchId": "match-1783707161123",
          "playerId": 1,
          "playerName": "P1",
          "tick": 90,
          "command": {
            "action": "train",
            "target": "unit-1"
          },
          "isValid": true,
          "timestamp": "2026-07-10T18:12:41.124Z"
        },
        "timestamp": "2026-07-10T18:12:41.124Z"
      },
      {
        "event": "observation:received",
        "data": {
          "matchId": "match-1783707161123",
          "playerId": 1,
          "playerName": "P1",
          "tick": 95,
          "observation": {
            "gameTime": 9.5,
            "resources": {
              "wood": 827.8588611228531,
              "stone": 526.5012639976087,
              "food": 569.2086396784633
            },
            "units": 38,
            "buildings": 14
          },
          "timestamp": "2026-07-10T18:12:41.124Z"
        },
        "timestamp": "2026-07-10T18:12:41.124Z"
      },
      {
        "event": "decision:completed",
        "data": {
          "matchId": "match-1783707161123",
          "playerId": 1,
          "playerName": "P1",
          "tick": 95,
          "model": "model-a",
          "prompt": "prompt-a",
          "decision": {
            "objective": "Prepare for endgame",
            "confidence": 0.9433533758888366,
            "reasoning": "Strategic decision based on game state"
          },
          "latency": 1131.360573160078,
          "cost": 0.0001,
          "timestamp": "2026-07-10T18:12:41.124Z"
        },
        "timestamp": "2026-07-10T18:12:41.124Z"
      },
      {
        "event": "command:executed",
        "data": {
          "matchId": "match-1783707161123",
          "playerId": 1,
          "playerName": "P1",
          "tick": 95,
          "command": {
            "action": "train",
            "target": "unit-89"
          },
          "isValid": true,
          "timestamp": "2026-07-10T18:12:41.124Z"
        },
        "timestamp": "2026-07-10T18:12:41.124Z"
      },
      {
        "event": "observation:received",
        "data": {
          "matchId": "match-1783707161123",
          "playerId": 1,
          "playerName": "P1",
          "tick": 100,
          "observation": {
            "gameTime": 10,
            "resources": {
              "wood": 562.9270259979397,
              "stone": 379.7052563021729,
              "food": 598.6350680194258
            },
            "units": 20,
            "buildings": 14
          },
          "timestamp": "2026-07-10T18:12:41.124Z"
        },
        "timestamp": "2026-07-10T18:12:41.124Z"
      },
      {
        "event": "decision:completed",
        "data": {
          "matchId": "match-1783707161123",
          "playerId": 1,
          "playerName": "P1",
          "tick": 100,
          "model": "model-a",
          "prompt": "prompt-a",
          "decision": {
            "objective": "Prepare for endgame",
            "confidence": 0.9103661291752605,
            "reasoning": "Strategic decision based on game state"
          },
          "latency": 1071.4298235188833,
          "cost": 0.0001,
          "timestamp": "2026-07-10T18:12:41.124Z"
        },
        "timestamp": "2026-07-10T18:12:41.124Z"
      },
      {
        "event": "command:executed",
        "data": {
          "matchId": "match-1783707161123",
          "playerId": 1,
          "playerName": "P1",
          "tick": 100,
          "command": {
            "action": "build",
            "target": "unit-24"
          },
          "isValid": true,
          "timestamp": "2026-07-10T18:12:41.124Z"
        },
        "timestamp": "2026-07-10T18:12:41.124Z"
      },
      {
        "event": "match:ended",
        "data": {
          "matchId": "match-1783707161123",
          "winner": {
            "id": 1,
            "name": "P1"
          },
          "runners": [
            {
              "id": 2,
              "name": "P2"
            }
          ],
          "duration": {
            "ticks": 100,
            "seconds": 10
          },
          "statistics": {
            "totalCommands": 110,
            "avgLatency": 1376,
            "totalCost": 0.049129916942596566,
            "commandSuccessRate": 0.9020971026474559
          },
          "timestamp": "2026-07-10T18:12:41.124Z"
        },
        "timestamp": "2026-07-10T18:12:41.124Z"
      }
    ],
    "statistics": {
      "totalEvents": 65,
      "eventCounts": {
        "match:started": 1,
        "observation:received": 21,
        "decision:completed": 21,
        "command:executed": 21,
        "match:ended": 1
      },
      "matches": 1,
      "errors": 0,
      "lastEvent": "match:ended"
    }
  },
  "summary": {
    "matchId": "match-1783707161123",
    "map": "alpine_mountains_3p",
    "players": 3,
    "status": "stopped",
    "duration": "0h 0m 0s",
    "ticks": 100
  }
}